zkdatabuilder/__init__.py
zkdatabuilder/circularDNA.py
zkdatabuilder/data.py
zkdatabuilder/zkdatabuilder.py
zkdatabuilder-0.1.4.dist-info/LICENCE.txt
zkdatabuilder-0.1.4.dist-info/METADATA
zkdatabuilder-0.1.4.dist-info/WHEEL
zkdatabuilder-0.1.4.dist-info/top_level.txt
zkdatabuilder-0.1.4.dist-info/RECORD
