Metadata-Version: 2.1
Name: zkdatabuilder
Version: 0.1.4
Summary: Builds E.coli model with DNA, free and bound transcription factors data file for lammps mimicing real bp density of E.coli
Home-page: UNKNOWN
Author: Zafer Kosar
Author-email: zafer.kosar.physics@gmail.com
License: MIT
Keywords: data file,lammps,lammps data file,E. coli model
Platform: UNKNOWN
Classifier: Development Status :: 4 - Beta
Classifier: Intended Audience :: Education
Classifier: License :: OSI Approved :: MIT License
Classifier: Programming Language :: Python :: 3
Requires-Dist: numpy
